odoo9_addon_stock_picking_operation_quick_change-9.0.1.0.0-py2.7-nspkg.pth
odoo_addons/stock_picking_operation_quick_change/__openerp__.py
odoo_addons/stock_picking_operation_quick_change/__init__.py
odoo_addons/stock_picking_operation_quick_change/README.rst
odoo_addons/stock_picking_operation_quick_change/i18n/es.po
odoo_addons/stock_picking_operation_quick_change/views/stock_picking_view.xml
odoo_addons/stock_picking_operation_quick_change/wizards/stock_picking_wizard.py
odoo_addons/stock_picking_operation_quick_change/wizards/stock_picking_wizard_view.xml
odoo_addons/stock_picking_operation_quick_change/wizards/__init__.py
odoo_addons/stock_picking_operation_quick_change/tests/test_stock_picking_operation_quick_change.py
odoo_addons/stock_picking_operation_quick_change/tests/__init__.py
odoo_addons/stock_picking_operation_quick_change/static/description/icon.svg
odoo_addons/stock_picking_operation_quick_change/static/description/icon.png
odoo9_addon_stock_picking_operation_quick_change-9.0.1.0.0.dist-info/top_level.txt
odoo9_addon_stock_picking_operation_quick_change-9.0.1.0.0.dist-info/WHEEL
odoo9_addon_stock_picking_operation_quick_change-9.0.1.0.0.dist-info/RECORD
odoo9_addon_stock_picking_operation_quick_change-9.0.1.0.0.dist-info/metadata.json
odoo9_addon_stock_picking_operation_quick_change-9.0.1.0.0.dist-info/DESCRIPTION.rst
odoo9_addon_stock_picking_operation_quick_change-9.0.1.0.0.dist-info/METADATA
odoo9_addon_stock_picking_operation_quick_change-9.0.1.0.0.dist-info/namespace_packages.txt
